{
  "Internal": {
    "FeatureSettingTexts": {
      "TheArchive.Features.Dev.RedirectSettings.Name": {
        "FName": {
          "English": "Redirect Settings",
          "Chinese": "重定向设置",
          "French": null,
          "Italian": null,
          "German": null,
          "Spanish": null,
          "Russian": null,
          "Portuguese_Brazil": null,
          "Polish": null,
          "Japanese": null,
          "Korean": null
        }
      },
      "TheArchive.Features.Dev.RedirectSettings.Description": {
        "FDescription": {
          "English": "Redirect settings load/save location",
          "Chinese": "重定向设置加载/保存位置",
          "French": null,
          "Italian": null,
          "German": null,
          "Spanish": null,
          "Russian": null,
          "Portuguese_Brazil": null,
          "Polish": null,
          "Japanese": null,
          "Korean": null
        }
      }
    },
    "EnumTexts": {}
  },
  "External": {
    "FeatureSettingTexts": {},
    "EnumTexts": {}
  },
  "GenericTexts": {}
}